odoo9_addon_account_product_fiscal_classification-9.0.1.0.0.99.dev52-py3.8-nspkg.pth
odoo_addons/account_product_fiscal_classification/README.rst
odoo_addons/account_product_fiscal_classification/__init__.py
odoo_addons/account_product_fiscal_classification/__openerp__.py
odoo_addons/account_product_fiscal_classification/demo/account_product_fiscal_classification.yml
odoo_addons/account_product_fiscal_classification/demo/account_product_fiscal_classification_template.yml
odoo_addons/account_product_fiscal_classification/demo/account_tax.yml
odoo_addons/account_product_fiscal_classification/demo/account_tax_template.yml
odoo_addons/account_product_fiscal_classification/demo/product_category.xml
odoo_addons/account_product_fiscal_classification/demo/product_template.yml
odoo_addons/account_product_fiscal_classification/demo/res_company.yml
odoo_addons/account_product_fiscal_classification/demo/res_groups.yml
odoo_addons/account_product_fiscal_classification/demo/res_users.yml
odoo_addons/account_product_fiscal_classification/i18n/account_product_fiscal_classification.pot
odoo_addons/account_product_fiscal_classification/i18n/am.po
odoo_addons/account_product_fiscal_classification/i18n/ar.po
odoo_addons/account_product_fiscal_classification/i18n/bg.po
odoo_addons/account_product_fiscal_classification/i18n/bs.po
odoo_addons/account_product_fiscal_classification/i18n/ca.po
odoo_addons/account_product_fiscal_classification/i18n/ca_ES.po
odoo_addons/account_product_fiscal_classification/i18n/cs.po
odoo_addons/account_product_fiscal_classification/i18n/da.po
odoo_addons/account_product_fiscal_classification/i18n/de.po
odoo_addons/account_product_fiscal_classification/i18n/el_GR.po
odoo_addons/account_product_fiscal_classification/i18n/en_AU.po
odoo_addons/account_product_fiscal_classification/i18n/en_GB.po
odoo_addons/account_product_fiscal_classification/i18n/en_US.po
odoo_addons/account_product_fiscal_classification/i18n/es.po
odoo9_addon_account_product_fiscal_classification-9.0.1.0.0.99.dev52.dist-info/METADATA
odoo9_addon_account_product_fiscal_classification-9.0.1.0.0.99.dev52.dist-info/WHEEL
odoo9_addon_account_product_fiscal_classification-9.0.1.0.0.99.dev52.dist-info/namespace_packages.txt
odoo9_addon_account_product_fiscal_classification-9.0.1.0.0.99.dev52.dist-info/top_level.txt
odoo9_addon_account_product_fiscal_classification-9.0.1.0.0.99.dev52.dist-info/RECORD
